certbot_dns_synergy_wholesale.py
certbot_dns_synergy_wholesale-2.0.1.dist-info/METADATA
certbot_dns_synergy_wholesale-2.0.1.dist-info/WHEEL
certbot_dns_synergy_wholesale-2.0.1.dist-info/entry_points.txt
certbot_dns_synergy_wholesale-2.0.1.dist-info/licenses/LICENSE
certbot_dns_synergy_wholesale-2.0.1.dist-info/RECORD
