Metadata-Version: 2.4
Name: certbot-dns-synergy-wholesale
Version: 2.0.1
Summary: A Synergy Wholesale DNS plugin for Cerbot to authenticate and retrieve Lets Encrypt certificates
Project-URL: Repository, https://github.com/ALameLlama/certbot-dns-synergy-wholesale
Author-email: Nicholas Ciechanowski <nicholas@ciech.anow.ski>
License-Expression: Apache-2.0
License-File: LICENSE
Requires-Python: >=3.10
Requires-Dist: certbot>=5
Requires-Dist: publicsuffixlist>=1.0.2.20250710
Requires-Dist: pytest>=8.4.2
Requires-Dist: ruff>=0.13.1
Requires-Dist: zeep<5,>=4.2.1
